llama_cookbook/finetuning.py
llama_cookbook/configs/__init__.py
llama_cookbook/configs/datasets.py
llama_cookbook/configs/fsdp.py
llama_cookbook/configs/peft.py
llama_cookbook/configs/quantization.py
llama_cookbook/configs/training.py
llama_cookbook/configs/wandb.py
llama_cookbook/data/__init__.py
llama_cookbook/data/concatenator.py
llama_cookbook/data/sampler.py
llama_cookbook/data/llama_guard/README.md
llama_cookbook/data/llama_guard/__init__.py
llama_cookbook/data/llama_guard/finetuning_data_formatter.py
llama_cookbook/data/llama_guard/finetuning_data_formatter_example.py
llama_cookbook/datasets/__init__.py
llama_cookbook/datasets/alpaca_dataset.py
llama_cookbook/datasets/custom_dataset.py
llama_cookbook/datasets/samsum_dataset.py
llama_cookbook/datasets/toxicchat_dataset.py
llama_cookbook/datasets/grammar_dataset/__init__.py
llama_cookbook/datasets/grammar_dataset/grammar_dataset.py
llama_cookbook/datasets/grammar_dataset/grammar_dataset_process.ipynb
llama_cookbook/inference/__init__.py
llama_cookbook/inference/chat_utils.py
llama_cookbook/inference/checkpoint_converter_fsdp_hf.py
llama_cookbook/inference/llm.py
llama_cookbook/inference/model_utils.py
llama_cookbook/inference/prompt_format_utils.py
llama_cookbook/inference/safety_utils.py
llama_cookbook/model_checkpointing/__init__.py
llama_cookbook/model_checkpointing/checkpoint_handler.py
llama_cookbook/policies/__init__.py
llama_cookbook/policies/activation_checkpointing_functions.py
llama_cookbook/policies/anyprecision_optimizer.py
llama_cookbook/policies/mixed_precision.py
llama_cookbook/policies/wrapping.py
llama_cookbook/tools/README.md
llama_cookbook/tools/compare_llama_weights.py
llama_cookbook/tools/convert_hf_weights_to_llama.py
llama_cookbook/utils/__init__.py
llama_cookbook/utils/config_utils.py
llama_cookbook/utils/dataset_utils.py
llama_cookbook/utils/flop_utils.py
llama_cookbook/utils/fsdp_utils.py
llama_cookbook/utils/memory_utils.py
llama_cookbook/utils/plot_metrics.py
llama_cookbook-0.0.5.post1.dist-info/METADATA
llama_cookbook-0.0.5.post1.dist-info/WHEEL
llama_cookbook-0.0.5.post1.dist-info/RECORD
