Metadata-Version: 2.4
Name: llama-cookbook
Version: 0.0.5.post1
Summary: Llama-cookbook is a companion project to the Llama models. It's goal is to provide examples to quickly get started with fine-tuning for domain adaptation and how to run inference for the fine-tuned models.
Project-URL: Homepage, https://github.com/meta-llama/llama-cookbook
Project-URL: Bug Tracker, https://github.com/meta-llama/llama-cookbook/issues
Author-email: Hamid Shojanazeri <hamidnazeri@meta.com>, Matthias Reso <mreso@meta.com>, Geeta Chauhan <gchauhan@meta.com>
Classifier: License :: Other/Proprietary License
Classifier: Operating System :: OS Independent
Classifier: Programming Language :: Python :: 3
Requires-Python: >=3.8
Requires-Dist: accelerate
Requires-Dist: appdirs
Requires-Dist: bitsandbytes
Requires-Dist: black
Requires-Dist: black[jupyter]
Requires-Dist: chardet
Requires-Dist: codeshield
Requires-Dist: datasets
Requires-Dist: evaluate
Requires-Dist: faiss-gpu; python_version < '3.11'
Requires-Dist: fire
Requires-Dist: gradio
Requires-Dist: loralib
Requires-Dist: markupsafe==2.0.1
Requires-Dist: matplotlib
Requires-Dist: openai
Requires-Dist: optimum
Requires-Dist: peft
Requires-Dist: py7zr
Requires-Dist: pyyaml==6.0.1
Requires-Dist: rouge-score
Requires-Dist: scipy
Requires-Dist: sentence-transformers
Requires-Dist: sentencepiece
Requires-Dist: tabulate
Requires-Dist: torch>=2.2
Requires-Dist: transformers>=4.45.1
Requires-Dist: typing-extensions>=4.8.0
Requires-Dist: unstructured[pdf]
Provides-Extra: auditnlg
Requires-Dist: auditnlg; extra == 'auditnlg'
Provides-Extra: langchain
Requires-Dist: langchain; extra == 'langchain'
Requires-Dist: langchain-community; extra == 'langchain'
Requires-Dist: langchain-openai; extra == 'langchain'
Provides-Extra: tests
Requires-Dist: pytest-mock; extra == 'tests'
Provides-Extra: vllm
Requires-Dist: vllm; extra == 'vllm'
